__init__.py
example.py
example_package_ANDREMSILVEIRA-0.0.1.dist-info/WHEEL
example_package_ANDREMSILVEIRA-0.0.1.dist-info/METADATA
example_package_ANDREMSILVEIRA-0.0.1.dist-info/licenses/LICENSE
example_package_ANDREMSILVEIRA-0.0.1.dist-info/RECORD
