Metadata-Version: 2.1
Name: example_package_ANDREMSILVEIRA
Version: 0.0.1
Summary: Analise fundamentalista utilizando dados de demonstrativos contábeis de empresas listadas B3.
Author-email: Andre Amorim <andre.a.silveira@icloud.com>
Requires-Python: >=3.7
Classifier: License :: OSI Approved :: MIT License
Classifier: Operating System :: OS Independent
Classifier: Programming Language :: Python :: 3
Project-URL: Bug Tracker, https://github.com/pypa/sampleproject/issues
Project-URL: Homepage, https://github.com/pypa/sampleproject
